Workbook

Sheet TrialBalance
A1: Client A
A2: Rodeo Imagination Inc. : Groupe Client A Inc (Consolidated)
A3: Trial Balance
A4: End of Dec 2024
B6: en CAD | C6: en EUR
A7: Account | B7: Total | C7: vlookup du B/S et P&L | D7: Taux
A8: 10000 - BANK
A9: 10625 - Compte courant LCL - Client A SAS (EUR | B9: 303244.71 | C9: =IFERROR(VLOOKUP(A9,BalanceSheet!$A:$B,2,0),0) -> 202569.63 | D9: =IFERROR(B9/C9,0) -> 1.49699
A10: 10630 - Compte courant BNP - Client A SAS (EUR) | B10: 827350.54 | C10: =IFERROR(VLOOKUP(A10,BalanceSheet!$A:$B,2,0),0) -> 552676.06 | D10: =IFERROR(B10/C10,0) -> 1.49699
A11: Total - 10000 - BANK | B11: =SUM(B9:B10) -> 1130595.2 | C11: =IFERROR(VLOOKUP(A11,BalanceSheet!$A:$B,2,0),0) -> 755245.69 | D11: =IFERROR(B11/C11,0) -> 1.49699
A12: 12000 - ACCOUNTS RECEIVABLE | C12: =IFERROR(VLOOKUP(A12,BalanceSheet!$A:$B,2,0),0) -> 0 | D12: =IFERROR(B12/C12,0) -> 0
A13: 12100 - Comptes clients | B13: 391196.45 | C13: =IFERROR(VLOOKUP(A13,BalanceSheet!$A:$B,2,0),0) -> 261322.02 | D13: =IFERROR(B13/C13,0) -> 1.49699
A14: 12200 - Comptes clients - intercos | B14: 269062.31 | C14: =IFERROR(VLOOKUP(A14,BalanceSheet!$A:$B,2,0),0) -> 179735.54 | D14: =IFERROR(B14/C14,0) -> 1.49699
A15: Total - 12000 - ACCOUNTS RECEIVABLE | B15: =SUM(B13:B14) -> 660258.76 | C15: =IFERROR(VLOOKUP(A15,BalanceSheet!$A:$B,2,0),0) -> 441057.56 | D15: =IFERROR(B15/C15,0) -> 1.49699
A16: 13000 - SALES TAXES ON PURCHASE | C16: =IFERROR(VLOOKUP(A16,BalanceSheet!$A:$B,2,0),0) -> 0 | D16: =IFERROR(B16/C16,0) -> 0
A17: 13356 - TVA déductible s/aut.biens et sces | B17: 6283.6604 | C17: =IFERROR(VLOOKUP(A17,BalanceSheet!$A:$B,2,0),0) -> 4197.53 | D17: =IFERROR(B17/C17,0) -> 1.49699
A18: 13358 - TVA déductible sur achats intracommunautaires | B18: 57.783814 | C18: =IFERROR(VLOOKUP(A18,BalanceSheet!$A:$B,2,0),0) -> 38.6 | D18: =IFERROR(B18/C18,0) -> 1.49699
A19: Total - 13000 - SALES TAXES ON PURCHASE | B19: =SUM(B17:B18) -> 6341.4442 | C19: =IFERROR(VLOOKUP(A19,BalanceSheet!$A:$B,2,0),0) -> 4236.13 | D19: =IFERROR(B19/C19,0) -> 1.49699
A20: 14000 - UNBILLED RECEIVABLE | C20: =IFERROR(VLOOKUP(A20,BalanceSheet!$A:$B,2,0),0) -> 0 | D20: =IFERROR(B20/C20,0) -> 0
A21: 14100 - Travaux en cours | B21: 803652.81 | C21: =IFERROR(VLOOKUP(A21,BalanceSheet!$A:$B,2,0),0) -> 536845.81 | D21: =IFERROR(B21/C21,0) -> 1.49699
A22: Total - 14000 - UNBILLED RECEIVABLE | B22: =SUM(B21) -> 803652.81 | C22: =IFERROR(VLOOKUP(A22,BalanceSheet!$A:$B,2,0),0) -> 536845.81 | D22: =IFERROR(B22/C22,0) -> 1.49699
A23: 15000 - PREPAID EXPENSES | C23: =IFERROR(VLOOKUP(A23,BalanceSheet!$A:$B,2,0),0) -> 0 | D23: =IFERROR(B23/C23,0) -> 0
A24: 15100 - Frais payés d'avance | B24: 231.28495 | C24: =IFERROR(VLOOKUP(A24,BalanceSheet!$A:$B,2,0),0) -> 154.5 | D24: =IFERROR(B24/C24,0) -> 1.49699
A25: Total - 15000 - PREPAID EXPENSES | B25: =SUM(B24) -> 231.28495 | C25: =IFERROR(VLOOKUP(A25,BalanceSheet!$A:$B,2,0),0) -> 154.5 | D25: =IFERROR(B25/C25,0) -> 1.49699
A26: 17000 - INVESTMENTS | C26: =IFERROR(VLOOKUP(A26,BalanceSheet!$A:$B,2,0),0) -> 0 | D26: =IFERROR(B26/C26,0) -> 0
A27: 17100 - Dépôts de garantie LT | B27: 610019.88 | C27: =IFERROR(VLOOKUP(A27,BalanceSheet!$A:$B,2,0),0) -> 407497.63 | D27: =IFERROR(B27/C27,0) -> 1.49699
A28: Total - 17000 - INVESTMENTS | B28: =SUM(B27) -> 610019.88 | C28: =IFERROR(VLOOKUP(A28,BalanceSheet!$A:$B,2,0),0) -> 407497.63 | D28: =IFERROR(B28/C28,0) -> 1.49699
A29: 18000 - FIXED ASSETS | C29: =IFERROR(VLOOKUP(A29,BalanceSheet!$A:$B,2,0),0) -> 0 | D29: =IFERROR(B29/C29,0) -> 0
A30: 18010 - Ameliorations locatives | B30: 46735.324 | C30: =IFERROR(VLOOKUP(A30,BalanceSheet!$A:$B,2,0),0) -> 31219.53 | D30: =IFERROR(B30/C30,0) -> 1.49699
A31: 18020 - Amort. cum. ameliorations locatives | B31: -4047.0526 | C31: =IFERROR(VLOOKUP(A31,BalanceSheet!$A:$B,2,0),0) -> -2703.46 | D31: =IFERROR(B31/C31,0) -> 1.49699
A32: 18110 - Équipements informatique | B32: 237033.07 | C32: =IFERROR(VLOOKUP(A32,BalanceSheet!$A:$B,2,0),0) -> 158339.78 | D32: =IFERROR(B32/C32,0) -> 1.49699
A33: 18120 - Amort cum. Équip. informatique | B33: -145853.38 | C33: =IFERROR(VLOOKUP(A33,BalanceSheet!$A:$B,2,0),0) -> -97431.1 | D33: =IFERROR(B33/C33,0) -> 1.49699
A34: 18310 - Équipement de photographie | B34: 9899.2356 | C34: =IFERROR(VLOOKUP(A34,BalanceSheet!$A:$B,2,0),0) -> 6612.76 | D34: =IFERROR(B34/C34,0) -> 1.49699
A35: 18320 - Amort. cum. Équip. photographie | B35: -1789.2773 | C35: =IFERROR(VLOOKUP(A35,BalanceSheet!$A:$B,2,0),0) -> -1195.25 | D35: =IFERROR(B35/C35,0) -> 1.49699
A36: 18350 - Équipement Audio | B36: 39019.104 | C36: =IFERROR(VLOOKUP(A36,BalanceSheet!$A:$B,2,0),0) -> 26065.04 | D36: =IFERROR(B36/C36,0) -> 1.49699
A37: 18360 - Amort.cum.équip. Audio | B37: -15220.466 | C37: =IFERROR(VLOOKUP(A37,BalanceSheet!$A:$B,2,0),0) -> -10167.38 | D37: =IFERROR(B37/C37,0) -> 1.49699
A38: 18410 - Mobilier de bureau & matériel | B38: 20427.551 | C38: =IFERROR(VLOOKUP(A38,BalanceSheet!$A:$B,2,0),0) -> 13645.75 | D38: =IFERROR(B38/C38,0) -> 1.49699
A39: 18420 - Amort. cum. - Matér./mobil./inst. | B39: -5772.8126 | C39: =IFERROR(VLOOKUP(A39,BalanceSheet!$A:$B,2,0),0) -> -3856.28 | D39: =IFERROR(B39/C39,0) -> 1.49699
A40: Total - 18000 - FIXED ASSETS | B40: =SUM(B30:B39) -> 180431.29 | C40: =IFERROR(VLOOKUP(A40,BalanceSheet!$A:$B,2,0),0) -> 120529.39 | D40: =IFERROR(B40/C40,0) -> 1.49699
A41: 21000 - ACCOUNTS PAYABLE | C41: =IFERROR(VLOOKUP(A41,BalanceSheet!$A:$B,2,0),0) -> 0 | D41: =IFERROR(B41/C41,0) -> 0
A42: 21010 - Comptes fournisseurs | B42: -47623.279 | C42: =IFERROR(VLOOKUP(A42,BalanceSheet!$A:$B,2,0),0) -> 31812.69 | D42: =IFERROR(B42/C42,0) -> -1.49699
A43: Total - 21000 - ACCOUNTS PAYABLE | B43: =SUM(B42) -> -47623.279 | C43: =IFERROR(VLOOKUP(A43,BalanceSheet!$A:$B,2,0),0) -> 31812.69 | D43: =IFERROR(B43/C43,0) -> -1.49699
A44: 22000 - ACCRUED LIABILITIES | C44: =IFERROR(VLOOKUP(A44,BalanceSheet!$A:$B,2,0),0) -> 0 | D44: =IFERROR(B44/C44,0) -> 0
A45: 22100 - Frais courus à payer | B45: -108278.56 | C45: =IFERROR(VLOOKUP(A45,BalanceSheet!$A:$B,2,0),0) -> 72330.85 | D45: =IFERROR(B45/C45,0) -> -1.49699
A46: 22205 - Provision perte de change | B46: -605.09833 | C46: =IFERROR(VLOOKUP(A46,BalanceSheet!$A:$B,2,0),0) -> 404.21 | D46: =IFERROR(B46/C46,0) -> -1.49699
A47: 22210 - Etat - Charges à payer | B47: -5562.8148 | C47: =IFERROR(VLOOKUP(A47,BalanceSheet!$A:$B,2,0),0) -> 3716 | D47: =IFERROR(B47/C47,0) -> -1.49699
A48: Total - 22000 - ACCRUED LIABILITIES | B48: =SUM(B45:B47) -> -114446.47 | C48: =IFERROR(VLOOKUP(A48,BalanceSheet!$A:$B,2,0),0) -> 76451.06 | D48: =IFERROR(B48/C48,0) -> -1.49699
A49: 22400 - CREDIT CARDS PAYABLE | C49: =IFERROR(VLOOKUP(A49,BalanceSheet!$A:$B,2,0),0) -> 0 | D49: =IFERROR(B49/C49,0) -> 0
A50: 22435 - CB en attente de débit - Client A SAS (EUR) | B50: -15564.07 | C50: =IFERROR(VLOOKUP(A50,BalanceSheet!$A:$B,2,0),0) -> 10396.91 | D50: =IFERROR(B50/C50,0) -> -1.49699
A51: Total - 22400 - CREDIT CARDS PAYABLE | B51: =SUM(B50) -> -15564.07 | C51: =IFERROR(VLOOKUP(A51,BalanceSheet!$A:$B,2,0),0) -> 10396.91 | D51: =IFERROR(B51/C51,0) -> -1.49699
A52: 23000 - SALARIES PAYABLE | C52: =IFERROR(VLOOKUP(A52,BalanceSheet!$A:$B,2,0),0) -> 0 | D52: =IFERROR(B52/C52,0) -> 0
A53: 23010 - Salaires à payer | B53: 21.856054 | C53: =IFERROR(VLOOKUP(A53,BalanceSheet!$A:$B,2,0),0) -> -14.6 | D53: =IFERROR(B53/C53,0) -> -1.49699
A54: 23040 - Bonis à payer | B54: -152393.58 | C54: =IFERROR(VLOOKUP(A54,BalanceSheet!$A:$B,2,0),0) -> 101800 | D54: =IFERROR(B54/C54,0) -> -1.49699
A55: 23070 - Vacances à payer | B55: -75418.221 | C55: =IFERROR(VLOOKUP(A55,BalanceSheet!$A:$B,2,0),0) -> 50379.91 | D55: =IFERROR(B55/C55,0) -> -1.49699
A56: 23100 - Sécurité sociale (France) | B56: -75608.639 | C56: =IFERROR(VLOOKUP(A56,BalanceSheet!$A:$B,2,0),0) -> 50507.11 | D56: =IFERROR(B56/C56,0) -> -1.49699
A57: 23102 - Caisse de retraite (France) | B57: -51667.038 | C57: =IFERROR(VLOOKUP(A57,BalanceSheet!$A:$B,2,0),0) -> 34513.95 | D57: =IFERROR(B57/C57,0) -> -1.49699
A58: 23103 - Prélèvement à la source (France) | B58: -17836.606 | C58: =IFERROR(VLOOKUP(A58,BalanceSheet!$A:$B,2,0),0) -> 11914.98 | D58: =IFERROR(B58/C58,0) -> -1.49699
A59: 23104 - Etat taxe apprentissage (France) | B59: -550.90729 | C59: =IFERROR(VLOOKUP(A59,BalanceSheet!$A:$B,2,0),0) -> 368.01 | D59: =IFERROR(B59/C59,0) -> -1.49699
A60: Total - 23000 - SALARIES PAYABLE | B60: =SUM(B53:B59) -> -373453.14 | C60: =IFERROR(VLOOKUP(A60,BalanceSheet!$A:$B,2,0),0) -> 249469.36 | D60: =IFERROR(B60/C60,0) -> -1.49699
A61: 24000 - SALES TAXES ON SALES | C61: =IFERROR(VLOOKUP(A61,BalanceSheet!$A:$B,2,0),0) -> 0 | D61: =IFERROR(B61/C61,0) -> 0
A62: 24410 - TVA à décaisser | B62: -84397.302 | C62: =IFERROR(VLOOKUP(A62,BalanceSheet!$A:$B,2,0),0) -> 56378 | D62: =IFERROR(B62/C62,0) -> -1.49699
A63: 24411 - TVA collectée 20% | B63: -46136.618 | C63: =IFERROR(VLOOKUP(A63,BalanceSheet!$A:$B,2,0),0) -> 30819.59 | D63: =IFERROR(B63/C63,0) -> -1.49699
A64: 24413 - TVA due sur achats intracommunautaire | B64: -57.783814 | C64: =IFERROR(VLOOKUP(A64,BalanceSheet!$A:$B,2,0),0) -> 38.6 | D64: =IFERROR(B64/C64,0) -> -1.49699
A65: Total - 24000 - SALES TAXES ON SALES | B65: =SUM(B62:B64) -> -130591.7 | C65: =IFERROR(VLOOKUP(A65,BalanceSheet!$A:$B,2,0),0) -> 87236.19 | D65: =IFERROR(B65/C65,0) -> -1.49699
A66: 25000 - UNEARNED INCOME | C66: =IFERROR(VLOOKUP(A66,BalanceSheet!$A:$B,2,0),0) -> 0 | D66: =IFERROR(B66/C66,0) -> 0
A67: 25010 - Revenu reporté | B67: -173650.84 | C67: =IFERROR(VLOOKUP(A67,BalanceSheet!$A:$B,2,0),0) -> 116000 | D67: =IFERROR(B67/C67,0) -> -1.49699
A68: Total - 25000 - UNEARNED INCOME | B68: =SUM(B67) -> -173650.84 | C68: =IFERROR(VLOOKUP(A68,BalanceSheet!$A:$B,2,0),0) -> 116000 | D68: =IFERROR(B68/C68,0) -> -1.49699
A69: 27000 - ADVANCES PAYABLE | C69: =IFERROR(VLOOKUP(A69,BalanceSheet!$A:$B,2,0),0) -> 0 | D69: =IFERROR(B69/C69,0) -> 0
A70: 27200 - Avance de Client A Inc | B70: -1798201.6 | C70: =IFERROR(VLOOKUP(A70,BalanceSheet!$A:$B,2,0),0) -> 1201211.5 | D70: =IFERROR(B70/C70,0) -> -1.49699
A71: Total - 27000 - ADVANCES PAYABLE | B71: =SUM(B70) -> -1798201.6 | C71: =IFERROR(VLOOKUP(A71,BalanceSheet!$A:$B,2,0),0) -> 1201211.5 | D71: =IFERROR(B71/C71,0) -> -1.49699
A72: 28000 - INCOME TAXES PAYABLE | C72: =IFERROR(VLOOKUP(A72,BalanceSheet!$A:$B,2,0),0) -> 0 | D72: =IFERROR(B72/C72,0) -> 0
A73: 28505 - Impôt France à payer | B73: -92898.708 | C73: =IFERROR(VLOOKUP(A73,BalanceSheet!$A:$B,2,0),0) -> 62057 | D73: =IFERROR(B73/C73,0) -> -1.49699
A74: Total - 28000 - INCOME TAXES PAYABLE | B74: =SUM(B73) -> -92898.708 | C74: =IFERROR(VLOOKUP(A74,BalanceSheet!$A:$B,2,0),0) -> 62057 | D74: =IFERROR(B74/C74,0) -> -1.49699
A75: 30000 - SHARE CAPITAL | C75: =IFERROR(VLOOKUP(A75,BalanceSheet!$A:$B,2,0),0) -> 0 | D75: =IFERROR(B75/C75,0) -> 0
A76: 30250 - Actions ordinaires | B76: -1511.341 | C76: =IFERROR(VLOOKUP(A76,BalanceSheet!$A:$B,2,0),0) -> 1012 | D76: =IFERROR(B76/C76,0) -> -1.49342
A77: Total - 30000 - SHARE CAPITAL | B77: =SUM(B76) -> -1511.341 | C77: =IFERROR(VLOOKUP(A77,BalanceSheet!$A:$B,2,0),0) -> 1012 | D77: =IFERROR(B77/C77,0) -> -1.49342
A78: 31000 - RETAINED EARNINGS | C78: =IFERROR(VLOOKUP(A78,BalanceSheet!$A:$B,2,0),0) -> 0 | D78: =IFERROR(B78/C78,0) -> 0
A79: 31170 - Réserve légale | B79: -151.49539 | C79: =IFERROR(VLOOKUP(A79,BalanceSheet!$A:$B,2,0),0) -> 101.2 | D79: =IFERROR(B79/C79,0) -> -1.49699
A80: 31210 - Retained Earnings | B80: -177559.8 | C80: =IFERROR(VLOOKUP(A80,BalanceSheet!$A:$B,2,0),0) -> 0 | D80: =IFERROR(B80/C80,0) -> 0
A81: Total - 31000 - RETAINED EARNINGS | B81: =SUM(B79:B80) -> -177711.3 | C81: =IFERROR(VLOOKUP(A81,BalanceSheet!$A:$B,2,0),0) -> 101.2 | D81: =IFERROR(B81/C81,0) -> -1756.0405
A82: 40000 - SALES | C82: =IFERROR(VLOOKUP(A82,BalanceSheet!$A:$B,2,0),0) -> 0 | D82: =IFERROR(B82/C82,0) -> 0
A83: 42000 - SALES REVENUE | C83: =IFERROR(VLOOKUP(A83,BalanceSheet!$A:$B,2,0),0) -> 0 | D83: =IFERROR(B83/C83,0) -> 0
A84: 42100 - Ventes | B84: -3523095.2 | C84: =IFERROR(VLOOKUP(A84,ProfitandLoss!$A:$B,2,0),0) -> 2381881.6 | D84: =IFERROR(B84/C84,0) -> -1.4791227
A85: 42110 - Prestations de services - Europe | B85: -24235.637 | C85: =IFERROR(VLOOKUP(A85,ProfitandLoss!$A:$B,2,0),0) -> 16546.22 | D85: =IFERROR(B85/C85,0) -> -1.4647235
A86: 42200 - Revenus - intercos | B86: -2058137.3 | C86: =IFERROR(VLOOKUP(A86,ProfitandLoss!$A:$B,2,0),0) -> 1389978.1 | D86: =IFERROR(B86/C86,0) -> -1.4806976
A87: Total - 42000 - SALES REVENUE | B87: =SUM(B84:B86) -> -5605468.2 | C87: =IFERROR(VLOOKUP(A87,ProfitandLoss!$A:$B,2,0),0) -> 3788406 | D87: =IFERROR(B87/C87,0) -> -1.4796377
A88: 43000 - UNEARNED REVENUE | C88: =IFERROR(VLOOKUP(A88,ProfitandLoss!$A:$B,2,0),0) -> 0 | D88: =IFERROR(B88/C88,0) -> 0
A89: 43100 - Variation TEC/RR | B89: -118443.16 | C89: =IFERROR(VLOOKUP(A89,ProfitandLoss!$A:$B,2,0),0) -> 76598.05 | D89: =IFERROR(B89/C89,0) -> -1.5462947
A90: Total - 43000 - UNEARNED REVENUE | B90: =SUM(B89) -> -118443.16 | C90: =IFERROR(VLOOKUP(A90,ProfitandLoss!$A:$B,2,0),0) -> 76598.05 | D90: =IFERROR(B90/C90,0) -> -1.5462947
A91: 44000 - OTHER REVENUE | C91: =IFERROR(VLOOKUP(A91,ProfitandLoss!$A:$B,2,0),0) -> 0 | D91: =IFERROR(B91/C91,0) -> 0
A92: 44220 - Autres revenus | B92: -1511.3799 | C92: =IFERROR(VLOOKUP(A92,ProfitandLoss!$A:$B,2,0),0) -> 1027.57 | D92: =IFERROR(B92/C92,0) -> -1.4708291
A93: Total - 44000 - OTHER REVENUE | B93: =SUM(B92) -> -1511.3799 | C93: =IFERROR(VLOOKUP(A93,ProfitandLoss!$A:$B,2,0),0) -> 1027.57 | D93: =IFERROR(B93/C93,0) -> -1.4708291
A94: Total - 40000 - SALES | B94: =SUM(B87,B90,B93) -> -5725422.7 | C94: =IFERROR(VLOOKUP(A94,ProfitandLoss!$A:$B,2,0),0) -> 3866031.6 | D94: =IFERROR(B94/C94,0) -> -1.480956
A95: 50000 - COST OF SALES | C95: =IFERROR(VLOOKUP(A95,ProfitandLoss!$A:$B,2,0),0) -> 0 | D95: =IFERROR(B95/C95,0) -> 0
A96: 51000 - SALARIES AND SOCIAL CHARGES | C96: =IFERROR(VLOOKUP(A96,ProfitandLoss!$A:$B,2,0),0) -> 0 | D96: =IFERROR(B96/C96,0) -> 0
A97: 51100 - Salaire COGS | C97: =IFERROR(VLOOKUP(A97,ProfitandLoss!$A:$B,2,0),0) -> 1260791.9 | D97: =IFERROR(B97/C97,0) -> 0
A98: 51100 - Salaire COGS | B98: 1868092.1 | C98: =IFERROR(VLOOKUP(A98,ProfitandLoss!$A:$B,2,0),0) -> 1260791.9 | D98: =IFERROR(B98/C98,0) -> 1.4816816
A99: Total - 51100 - Salaire COGS | B99: =SUM(B98) -> 1868092.1 | C99: =IFERROR(VLOOKUP(A99,ProfitandLoss!$A:$B,2,0),0) -> 0 | D99: =IFERROR(B99/C99,0) -> 0
A100: 51101 - Indemnités et avantages divers COGS (France) | B100: 15178.634 | C100: =IFERROR(VLOOKUP(A100,ProfitandLoss!$A:$B,2,0),0) -> 10219.05 | D100: =IFERROR(B100/C100,0) -> 1.4853273
A101: 51206 - Cotisations à l'URSSAF COGS (France) | B101: 440606.09 | C101: =IFERROR(VLOOKUP(A101,ProfitandLoss!$A:$B,2,0),0) -> 297486.35 | D101: =IFERROR(B101/C101,0) -> 1.4810968
...

Sheet BalanceSheet
A1: Client A
A2: Rodeo Imagination Inc. : Groupe Client A Inc : Client A Inc. : Client A SAS
A3: Balance Sheet
A4: End of Dec 2024
A5: en Euro
A7: Financial Row | B7: Amount
A8: Current Assets
A9: Bank
A10: 10000 - BANK
A11: 10625 - Compte courant LCL - Client A SAS (EUR | B11: 202569.63
A12: 10630 - Compte courant BNP - Client A SAS (EUR) | B12: 552676.06
A13: Total - 10000 - BANK | B13: =SUM(B11:B12) -> 755245.69
A14: Total Bank | B14: =SUM(B13) -> 755245.69
A15: Accounts Receivable
A16: 12000 - ACCOUNTS RECEIVABLE
A17: 12100 - Comptes clients | B17: 261322.02
A18: 12200 - Comptes clients - intercos | B18: 179735.54
A19: Total - 12000 - ACCOUNTS RECEIVABLE | B19: =SUM(B17:B18) -> 441057.56
A20: Total Accounts Receivable | B20: =SUM(B19) -> 441057.56
A21: Unbilled Receivable
A22: 14000 - UNBILLED RECEIVABLE
A23: 14100 - Travaux en cours | B23: 536845.81
A24: Total - 14000 - UNBILLED RECEIVABLE | B24: =SUM(B23) -> 536845.81
A25: Total Unbilled Receivable | B25: =SUM(B24) -> 536845.81
A26: Other Current Asset
A27: 13000 - SALES TAXES ON PURCHASE
A28: 13356 - TVA déductible s/aut.biens et sces | B28: 4197.53
A29: 13358 - TVA déductible sur achats intracommunautaires | B29: 38.6
A30: Total - 13000 - SALES TAXES ON PURCHASE | B30: =SUM(B28:B29) -> 4236.13
A31: 15000 - PREPAID EXPENSES
A32: 15100 - Frais payés d'avance | B32: 154.5
A33: Total - 15000 - PREPAID EXPENSES | B33: =SUM(B32) -> 154.5
A34: Total Other Current Asset | B34: =SUM(B30,B33) -> 4390.63
A35: Total Current Assets | B35: =B14+B20+B25+B34 -> 1737539.7
A36: Fixed Assets
A37: 18000 - FIXED ASSETS
A38: 18010 - Ameliorations locatives | B38: 31219.53
A39: 18020 - Amort. cum. ameliorations locatives | B39: -2703.46
A40: 18110 - Équipements informatique | B40: 158339.78
A41: 18120 - Amort cum. Équip. informatique | B41: -97431.1
A42: 18310 - Équipement de photographie | B42: 6612.76
A43: 18320 - Amort. cum. Équip. photographie | B43: -1195.25
A44: 18350 - Équipement Audio | B44: 26065.04
A45: 18360 - Amort.cum.équip. Audio | B45: -10167.38
A46: 18410 - Mobilier de bureau & matériel | B46: 13645.75
A47: 18420 - Amort. cum. - Matér./mobil./inst. | B47: -3856.28
A48: Total - 18000 - FIXED ASSETS | B48: =SUM(B38:B47) -> 120529.39
A49: Total Fixed Assets | B49: =SUM(B48) -> 120529.39
A50: Other Assets
A51: 17000 - INVESTMENTS
A52: 17100 - Dépôts de garantie LT | B52: 407497.63
A53: Total - 17000 - INVESTMENTS | B53: =SUM(B52) -> 407497.63
A54: Total Other Assets | B54: =SUM(B53) -> 407497.63
A55: Current Liabilities
A56: Accounts Payable
A57: 21000 - ACCOUNTS PAYABLE
A58: 21010 - Comptes fournisseurs | B58: 31812.69
A59: Total - 21000 - ACCOUNTS PAYABLE | B59: =SUM(B58) -> 31812.69
A60: Total Accounts Payable | B60: =SUM(B59) -> 31812.69
A61: Credit Card
A62: 22400 - CREDIT CARDS PAYABLE
A63: 22435 - CB en attente de débit - Client A SAS (EUR) | B63: 10396.91
A64: Total - 22400 - CREDIT CARDS PAYABLE | B64: =SUM(B63) -> 10396.91
A65: Total Credit Card | B65: =SUM(B64) -> 10396.91
A66: Other Current Liability
A67: 22000 - ACCRUED LIABILITIES
A68: 22100 - Frais courus à payer | B68: 72330.85
A69: 22205 - Provision perte de change | B69: 404.21
A70: 22210 - Etat - Charges à payer | B70: 3716
A71: Total - 22000 - ACCRUED LIABILITIES | B71: =SUM(B68:B70) -> 76451.06
A72: 23000 - SALARIES PAYABLE
A73: 23010 - Salaires à payer | B73: -14.6
A74: 23040 - Bonis à payer | B74: 101800
A75: 23070 - Vacances à payer | B75: 50379.91
A76: 23100 - Sécurité sociale (France) | B76: 50507.11
A77: 23102 - Caisse de retraite (France) | B77: 34513.95
A78: 23103 - Prélèvement à la source (France) | B78: 11914.98
A79: 23104 - Etat taxe apprentissage (France) | B79: 368.01
A80: Total - 23000 - SALARIES PAYABLE | B80: =SUM(B73:B79) -> 249469.36
A81: 24000 - SALES TAXES ON SALES
A82: 24410 - TVA à décaisser | B82: 56378
A83: 24411 - TVA collectée 20% | B83: 30819.59
A84: 24413 - TVA due sur achats intracommunautaire | B84: 38.6
A85: Total - 24000 - SALES TAXES ON SALES | B85: =SUM(B82:B84) -> 87236.19
A86: 25000 - UNEARNED INCOME
A87: 25010 - Revenu reporté | B87: 116000
A88: Total - 25000 - UNEARNED INCOME | B88: =SUM(B87) -> 116000
A89: 27000 - ADVANCES PAYABLE
A90: 27200 - Avance de Client A Inc | B90: 1201211.5
A91: Total - 27000 - ADVANCES PAYABLE | B91: =SUM(B90) -> 1201211.5
A92: 28000 - INCOME TAXES PAYABLE
A93: 28505 - Impôt France à payer | B93: 62057
A94: Total - 28000 - INCOME TAXES PAYABLE | B94: =SUM(B93) -> 62057
A95: Total Other Current Liability | B95: =SUM(B71,B80,B85,B88,B91,B94) -> 1792425.1
A96: Total Liabilities | B96: =B60+B65+B95 -> 1834634.7
A97: Current Assets Less Current Liabilities | B97: =B35-B96 -> -97095.01
A98: Total Assets Less Current Liabilities | B98: =B97+B49+B54 -> 430932.01
A99: Total Assets Less Total Liabilities | B99: =B98-0 -> 430932.01
A100: Capital and Reserves
A101: Capital and Reserves
...

Sheet ProfitandLoss
A1: Client A
A2: Rodeo Imagination Inc. : Groupe Client A Inc : Client A Inc. : Client A SAS
A3: Profit and Loss
A4: From Jan 2024 to Dec 2024
A5: en Euro
A7: Financial Row | B7: Amount
A8: Sales
A9: 40000 - SALES
A10: 42000 - SALES REVENUE
A11: 42100 - Ventes | B11: 2381881.6
A12: 42110 - Prestations de services - Europe | B12: 16546.22
A13: 42200 - Revenus - intercos | B13: 1389978.1
A14: Total - 42000 - SALES REVENUE | B14: =SUM(B11:B13) -> 3788406
A15: 43000 - UNEARNED REVENUE
A16: 43100 - Variation TEC/RR | B16: 76598.05
A17: Total - 43000 - UNEARNED REVENUE | B17: =SUM(B16) -> 76598.05
A18: 44000 - OTHER REVENUE
A19: 44220 - Autres revenus | B19: 1027.57
A20: Total - 44000 - OTHER REVENUE | B20: =SUM(B19) -> 1027.57
A21: Total - 40000 - SALES | B21: =SUM(B14,B17,B20) -> 3866031.6
A22: Total - Sales | B22: =SUM(B21) -> 3866031.6
A23: Purchases
A24: 50000 - COST OF SALES
A25: 51000 - SALARIES AND SOCIAL CHARGES
A26: 51100 - Salaire COGS | B26: 1260791.9
A27: 51101 - Indemnités et avantages divers COGS (France) | B27: 10219.05
A28: 51206 - Cotisations à l'URSSAF COGS (France) | B28: 297486.35
A29: 51207 - Taxe d'apprentissage COGS (France) | B29: 7810.48
A30: 51208 - Formation continue (Organisme) COGS (France) | B30: 18900.92
A31: 51209 - Cotisations aux mutuelles COGS (France) | B31: 231.97
A32: 51210 - Cotisations aux caisses de retraite COGS (France) | B32: 127689.43
A33: 51211 - Cotisations Pôle Emploi COGS (France) | B33: 76525.94
A34: 51212 - Cotisations autres organismes COGS (France) | B34: 113965.69
A35: 51300 - Boni COGS | B35: 72000
A36: Total - 51000 - SALARIES AND SOCIAL CHARGES | B36: =SUM(B26:B35) -> 1985621.7
A37: 52000 - SUBCONTRACTORS
A38: 52100 - Sous-traitants compagnies | B38: 92408.68
A39: 52200 - Sous-traitants - intercos | B39: 390009.13
A40: 52400 - Sous-traitants artistes | B40: 31630
A41: Total - 52000 - SUBCONTRACTORS | B41: =SUM(B38:B40) -> 514047.81
A42: 53000 - PRODUCTION EXPENSES
A43: 53100 - Repas Projets | B43: 9304.05
A44: 53150 - Frais de voyage et déplacement Projets | B44: 51969.09
A45: 53200 - Dépenses Projets | B45: 3110.97
A46: Total - 53000 - PRODUCTION EXPENSES | B46: =SUM(B43:B45) -> 64384.11
A47: Total - 50000 - COST OF SALES | B47: =SUM(B36,B41,B46) -> 2564053.6
A48: Total - Purchases | B48: =SUM(B47) -> 2564053.6
A49: Gross Profit | B49: =B22-B48 -> 1301978
A50: Overheads
A51: 60000 - ADMINISTRATIVE SALARIES AND SOCIAL CHARGES
A52: 60100 - Salaires | B52: 266202.65
A53: 60101 - Indemnités et avantages divers Admin (France) | B53: 7139.17
A54: 60151 - Cotisations à l'URSSAF Admin (France) | B54: 65343.8
A55: 60152 - Taxe d'apprentissage Admin (France) | B55: 1643.81
A56: 60153 - Formation continue (Organisme) Admin (France) | B56: 4751.4
A57: 60154 - Cotisations aux mutuelles Admin (France) | B57: 224.4
A58: 60155 - Cotisations aux caisses de retraite Admin (France) | B58: 26729.57
A59: 60156 - Cotisations Pôle Emploi Admin (France) | B59: 11309.23
A60: 60157 - Cotisations autres organismes Admin (France) | B60: 284.63
A61: Total - 60000 - ADMINISTRATIVE SALARIES AND SOCIAL CHARGES | B61: =SUM(B52:B60) -> 383628.66
A62: 61000 - SELLING AND ADMINISTRATIVE EXPENSES
A63: 62000 - PROFESSIONNAL FEES
A64: 62100 - Honoraires professionnels | B64: 56432
A65: 62200 - Frais légaux | B65: 20752
A66: 62300 - Consultant | B66: 12930.06
A67: Total - 62000 - PROFESSIONNAL FEES | B67: =SUM(B64:B66) -> 90114.06
A68: 63000 - TRAVEL EXPENSES
A69: 63010 - Frais de voyage et déplacement | B69: 6576.37
A70: Total - 63000 - TRAVEL EXPENSES | B70: =SUM(B69) -> 6576.37
A71: 64000 - MEALS
A72: 64010 - Repas | B72: 625.58
A73: Total - 64000 - MEALS | B73: =SUM(B72) -> 625.58
A74: 65000 - INSURANCE
A75: 65100 - Assurance commercial multirisques | B75: 3002.42
A76: Total - 65000 - INSURANCE | B76: =SUM(B75) -> 3002.42
A77: 66000 - BAD DEBT
A78: 66010 - Créances douteuses | B78: 404.21
A79: Total - 66000 - BAD DEBT | B79: =SUM(B78) -> 404.21
A80: 68000 - FACILITY EXPENSES
A81: 68010 - Loyer | B81: 223519.91
A82: 68030 - Chauffage et Électricité | B82: 27075.64
A83: 68090 - Réparation & Entretien local | B83: 19699.11
A84: 68110 - Frais de bureau | B84: 2978.86
A85: 68120 - Sécurité | B85: 1717.46
A86: 68135 - Taxes foncières/bureau (France) | B86: 5290.01
A87: 68150 - Frais de livraison | B87: 308.32
A88: 68170 - Épicerie | B88: 3006.05
A89: Total - 68000 - FACILITY EXPENSES | B89: =SUM(B81:B88) -> 283595.36
A90: 69000 - MARKETING AND COMMUNICATIONS EXPENSES
A91: 69090 - Promo | B91: 289.64
A92: 69110 - Commandites (et bourses) | B92: 500
A93: 69150 - Events & Awards | B93: 295.25
A94: 69170 - Événements corporatifs | B94: 4126.72
A95: 69190 - Comité social | B95: 151.47
A96: 69211 - Cadeaux clients | B96: 90.87
A97: 69212 - Cadeaux employés | B97: 3662.06
A98: Total - 69000 - MARKETING AND COMMUNICATIONS EXPENSES | B98: =SUM(B91:B97) -> 9116.01
A99: 70000 - HUMAN RESOURCE EXPENSES
A100: 70010 - Recrutement | B100: 1158.19
A101: 70030 - Formation | B101: 2400
...

Sheet Sheet2
